{
  "_class": "shapeGroup",
  "clippingMaskMode": 0,
  "do_objectID": "E1718C66-A786-4392-A928-9B38940D8A42",
  "exportOptions": {
    "_class": "exportOptions",
    "do_objectID": "E2CF273C-54D2-4AAA-8696-7F8DA2BEDDCF",
    "exportFormats": [
    ],
    "includedLayerIds": [
    ],
    "layerOptions": 0,
    "shouldTrim": false
  },
  "frame": {
    "_class": "rect",
    "constrainProportions": false,
    "do_objectID": "09E5B5ED-9E14-45C4-9EF5-71784E6CEF33",
    "height": 3.333333333333333,
    "width": 10,
    "x": 0,
    "y": 6.666666666666667
  },
  "hasClickThrough": false,
  "hasClippingMask": false,
  "isFlippedHorizontal": false,
  "isFlippedVertical": false,
  "isLocked": false,
  "isVisible": true,
  "layerListExpandedType": 1,
  "layers": [
    {
      "class": "shapePath",
      "id": "076A8E18-95C0-4D51-A557-6BE7D742A2A7"
    }
  ],
  "name": "Line Copy 2",
  "nameIsFixed": false,
  "resizingConstraint": 63,
  "resizingType": 0,
  "rotation": 0,
  "shouldBreakMaskChain": false,
  "style": {
    "_class": "style",
    "borderOptions": {
      "_class": "borderOptions",
      "dashPattern": [
      ],
      "do_objectID": "C5D370E9-65DB-4AC1-8FA8-D18D5A18BA5D",
      "isEnabled": false,
      "lineCapStyle": 2,
      "lineJoinStyle": 0
    },
    "borders": [
      {
        "_class": "border",
        "color": {
          "_class": "color",
          "alpha": 1,
          "blue": 0.09803921568627445,
          "green": 0.7019607843137254,
          "red": 0.9647058823529412
        },
        "fillType": 0,
        "isEnabled": true,
        "position": 0,
        "thickness": 1
      }
    ],
    "do_objectID": "E4E463CF-53B0-495C-AD54-6A5536D58E8F",
    "endDecorationType": 0,
    "fills": [
      {
        "_class": "fill",
        "color": {
          "_class": "color",
          "alpha": 1,
          "blue": 0.847,
          "green": 0.847,
          "red": 0.847
        },
        "fillType": 0,
        "isEnabled": false,
        "noiseIndex": 0,
        "noiseIntensity": 0,
        "patternFillType": 1,
        "patternTileScale": 1
      }
    ],
    "miterLimit": 10,
    "startDecorationType": 0
  },
  "windingRule": 1
}