{
  "_class": "shapeGroup",
  "clippingMaskMode": 0,
  "do_objectID": "7E45FC0F-8492-40BA-A466-EE4B0D89ACA4",
  "exportOptions": {
    "_class": "exportOptions",
    "do_objectID": "7538C885-D329-4189-8FD2-E82E9A9871F5",
    "exportFormats": [
    ],
    "includedLayerIds": [
    ],
    "layerOptions": 0,
    "shouldTrim": false
  },
  "frame": {
    "_class": "rect",
    "constrainProportions": false,
    "do_objectID": "69BE8ADC-05C1-4BD8-822C-7C95528812D5",
    "height": 50,
    "width": 375,
    "x": 0,
    "y": 0
  },
  "hasClickThrough": false,
  "hasClippingMask": false,
  "isFlippedHorizontal": false,
  "isFlippedVertical": false,
  "isLocked": false,
  "isVisible": true,
  "layerListExpandedType": 0,
  "layers": [
    {
      "class": "rectangle",
      "id": "16F871D5-6573-4129-A8E6-2458B3773E59"
    }
  ],
  "name": "Rectangle Copy 2",
  "nameIsFixed": false,
  "resizingConstraint": 63,
  "resizingType": 0,
  "rotation": 0,
  "shouldBreakMaskChain": false,
  "style": {
    "_class": "style",
    "borders": [
      {
        "_class": "border",
        "color": {
          "_class": "color",
          "alpha": 1,
          "blue": 0.3803921568627451,
          "green": 0.2588235294117646,
          "red": 0.09411764705882353
        },
        "fillType": 0,
        "isEnabled": true,
        "position": 1,
        "thickness": 1
      }
    ],
    "do_objectID": "17276C07-7CD8-45B1-A159-51D2AC2264C1",
    "endDecorationType": 0,
    "fills": [
      {
        "_class": "fill",
        "color": {
          "_class": "color",
          "alpha": 1,
          "blue": 0.3647058823529412,
          "green": 0.2470588235294118,
          "red": 0.07843137254901962
        },
        "fillType": 0,
        "isEnabled": true,
        "noiseIndex": 0,
        "noiseIntensity": 0,
        "patternFillType": 1,
        "patternTileScale": 1
      }
    ],
    "miterLimit": 10,
    "startDecorationType": 0
  },
  "windingRule": 1
}