{
  "_class": "group",
  "do_objectID": "5C9E51B0-E747-448F-9DE6-FACA19866A5F",
  "exportOptions": {
    "_class": "exportOptions",
    "do_objectID": "7D4E0CD8-9AA0-447E-84F8-C4A87DA5BC86",
    "exportFormats": [
    ],
    "includedLayerIds": [
    ],
    "layerOptions": 0,
    "shouldTrim": false
  },
  "frame": {
    "_class": "rect",
    "constrainProportions": false,
    "do_objectID": "AB7FFC28-1CFA-4FCF-87C5-C666C8A24DFE",
    "height": 167,
    "width": 361,
    "x": 0,
    "y": 0
  },
  "hasClickThrough": false,
  "isFlippedHorizontal": false,
  "isFlippedVertical": false,
  "isLocked": false,
  "isVisible": true,
  "layerListExpandedType": 0,
  "layers": [
    {
      "class": "shapeGroup",
      "id": "C3BD17EB-0EED-4B99-83F1-9221FF73AB3A"
    },
    {
      "class": "text",
      "id": "5CD07240-2915-4A59-A35B-F69FB3C27773"
    },
    {
      "class": "text",
      "id": "ECD04703-4159-494D-AB7B-334BF18924AB"
    },
    {
      "class": "shapeGroup",
      "id": "8737665E-F6D3-43A9-8D4F-844894FEE182"
    }
  ],
  "name": "brand details",
  "nameIsFixed": true,
  "resizingConstraint": 63,
  "resizingType": 0,
  "rotation": 0,
  "shouldBreakMaskChain": false,
  "style": {
    "_class": "style",
    "do_objectID": "4B6666E5-3F01-4456-8D02-0779E8A52536",
    "endDecorationType": 0,
    "miterLimit": 10,
    "startDecorationType": 0
  }
}