{
  "_class": "triangle",
  "booleanOperation": -1,
  "do_objectID": "90CC6911-8AF6-408F-9E43-BA9F158F7899",
  "edited": false,
  "exportOptions": {
    "_class": "exportOptions",
    "do_objectID": "A14AB302-62D2-4610-B499-B0D508BD043A",
    "exportFormats": [
    ],
    "includedLayerIds": [
    ],
    "layerOptions": 0,
    "shouldTrim": false
  },
  "frame": {
    "_class": "rect",
    "constrainProportions": false,
    "do_objectID": "E7071115-3166-4BE7-9CB7-F533DFC1221F",
    "height": 11.99999999999999,
    "width": 24.99999999999996,
    "x": 0,
    "y": 0
  },
  "isClosed": true,
  "isEquilateral": false,
  "isFlippedHorizontal": false,
  "isFlippedVertical": false,
  "isLocked": false,
  "isVisible": true,
  "layerListExpandedType": 0,
  "name": "Path",
  "nameIsFixed": false,
  "pointRadiusBehaviour": 0,
  "points": [
    {
      "_class": "curvePoint",
      "cornerRadius": 0,
      "curveFrom": "{0.5, 0}",
      "curveMode": 1,
      "curveTo": "{0.5, 0}",
      "hasCurveFrom": false,
      "hasCurveTo": false,
      "point": "{0.5, 0}"
    },
    {
      "_class": "curvePoint",
      "cornerRadius": 0,
      "curveFrom": "{1, 1}",
      "curveMode": 1,
      "curveTo": "{1, 1}",
      "hasCurveFrom": false,
      "hasCurveTo": false,
      "point": "{1, 1}"
    },
    {
      "_class": "curvePoint",
      "cornerRadius": 0,
      "curveFrom": "{0, 1}",
      "curveMode": 1,
      "curveTo": "{0, 1}",
      "hasCurveFrom": false,
      "hasCurveTo": false,
      "point": "{0, 1}"
    }
  ],
  "resizingConstraint": 63,
  "resizingType": 0,
  "rotation": 0,
  "shouldBreakMaskChain": false
}