{
  "_class": "shapeGroup",
  "clippingMaskMode": 0,
  "do_objectID": "3FE1E451-A606-4F70-B1CC-19A4F361374C",
  "exportOptions": {
    "_class": "exportOptions",
    "do_objectID": "102AFCEE-4FC5-4D4C-9694-DEECD34D7A74",
    "exportFormats": [
    ],
    "includedLayerIds": [
    ],
    "layerOptions": 0,
    "shouldTrim": false
  },
  "frame": {
    "_class": "rect",
    "constrainProportions": false,
    "do_objectID": "79987A94-113F-4355-B548-32BDB3C5B215",
    "height": 50,
    "width": 375,
    "x": 0,
    "y": 0
  },
  "hasClickThrough": false,
  "hasClippingMask": false,
  "isFlippedHorizontal": false,
  "isFlippedVertical": false,
  "isLocked": false,
  "isVisible": true,
  "layerListExpandedType": 0,
  "layers": [
    {
      "class": "rectangle",
      "id": "F92E428D-DE58-4DC1-A647-1949A724DF17"
    }
  ],
  "name": "Rectangle Copy 2",
  "nameIsFixed": false,
  "resizingConstraint": 63,
  "resizingType": 0,
  "rotation": 0,
  "shouldBreakMaskChain": false,
  "style": {
    "_class": "style",
    "borders": [
      {
        "_class": "border",
        "color": {
          "_class": "color",
          "alpha": 1,
          "blue": 0.3803921568627451,
          "green": 0.2588235294117646,
          "red": 0.09411764705882353
        },
        "fillType": 0,
        "isEnabled": true,
        "position": 1,
        "thickness": 1
      }
    ],
    "do_objectID": "D0CE3620-D337-4058-8C2E-5388691AA0A8",
    "endDecorationType": 0,
    "fills": [
      {
        "_class": "fill",
        "color": {
          "_class": "color",
          "alpha": 1,
          "blue": 0.3647058823529412,
          "green": 0.2470588235294118,
          "red": 0.07843137254901962
        },
        "fillType": 0,
        "isEnabled": true,
        "noiseIndex": 0,
        "noiseIntensity": 0,
        "patternFillType": 1,
        "patternTileScale": 1
      }
    ],
    "miterLimit": 10,
    "startDecorationType": 0
  },
  "windingRule": 1
}