{
  "_class": "shapePath",
  "booleanOperation": -1,
  "do_objectID": "B8070FBB-8FFC-4EF2-A029-FD8F65E1180A",
  "edited": true,
  "exportOptions": {
    "_class": "exportOptions",
    "exportFormats": [
    ],
    "includedLayerIds": [
    ],
    "layerOptions": 0,
    "shouldTrim": false
  },
  "frame": {
    "_class": "rect",
    "constrainProportions": false,
    "height": 49,
    "width": 2,
    "x": 0,
    "y": 0
  },
  "isClosed": false,
  "isFlippedHorizontal": false,
  "isFlippedVertical": false,
  "isLocked": false,
  "isVisible": true,
  "layerListExpandedType": 0,
  "name": "Path",
  "nameIsFixed": false,
  "pointRadiusBehaviour": 1,
  "points": [
    {
      "_class": "curvePoint",
      "cornerRadius": 0,
      "curveFrom": "{-8, -0.010204081632653069}",
      "curveMode": 1,
      "curveTo": "{-8, -0.010204081632653069}",
      "hasCurveFrom": false,
      "hasCurveTo": false,
      "point": "{0.49999999999999822, 0}"
    },
    {
      "_class": "curvePoint",
      "cornerRadius": 0,
      "curveFrom": "{-7.5, 0.010204081632653048}",
      "curveMode": 1,
      "curveTo": "{-7.5, 0.010204081632653048}",
      "hasCurveFrom": false,
      "hasCurveTo": false,
      "point": "{0.5, 1}"
    }
  ],
  "resizingConstraint": 63,
  "resizingType": 0,
  "rotation": 0,
  "shouldBreakMaskChain": false
}